{
  "last_update": "2026-04-27T14:23:41.576626+00:00",
  "totalItems": 31,
  "indices": [
    {
      "ticker": "^GSPC",
      "name": "S&P 500",
      "price": 7159.3301,
      "trend": -0.08,
      "currency": null,
      "unit": "pts"
    },
    {
      "ticker": "^DJI",
      "name": "Dow Jones",
      "price": 49179.7109,
      "trend": -0.1,
      "currency": null,
      "unit": "pts"
    },
    {
      "ticker": "^IXIC",
      "name": "Nasdaq",
      "price": 24764.1367,
      "trend": -0.29,
      "currency": null,
      "unit": "pts"
    },
    {
      "ticker": "^STOXX50E",
      "name": "Euro Stoxx 50",
      "price": 5871.9102,
      "trend": -0.2,
      "currency": null,
      "unit": "pts"
    },
    {
      "ticker": "^FTSE",
      "name": "FTSE 100",
      "price": 10351.3604,
      "trend": -0.27,
      "currency": null,
      "unit": "pts"
    },
    {
      "ticker": "^N225",
      "name": "Nikkei 225",
      "price": 60537.3594,
      "trend": 1.38,
      "currency": null,
      "unit": "pts"
    }
  ],
  "currencies": [
    {
      "ticker": "EURUSD=X",
      "name": "EUR / USD",
      "price": 1.1744,
      "trend": 0.51,
      "currency": null,
      "unit": null
    },
    {
      "ticker": "USDJPY=X",
      "name": "USD / JPY",
      "price": 159.237,
      "trend": -0.32,
      "currency": null,
      "unit": null
    },
    {
      "ticker": "GBPUSD=X",
      "name": "GBP / USD",
      "price": 1.3556,
      "trend": 0.66,
      "currency": null,
      "unit": null
    },
    {
      "ticker": "USDCNY=X",
      "name": "USD / CNY",
      "price": 6.8223,
      "trend": -0.05,
      "currency": null,
      "unit": null
    },
    {
      "ticker": "DX-Y.NYB",
      "name": "US Dollar Index",
      "price": 98.347,
      "trend": -0.17,
      "currency": null,
      "unit": "pts"
    },
    {
      "ticker": "USDMAD=X",
      "name": "USD / MAD",
      "price": 9.2434,
      "trend": -0.15,
      "currency": null,
      "unit": null
    },
    {
      "ticker": "EURMAD=X",
      "name": "EUR / MAD",
      "price": 10.843,
      "trend": 3.36,
      "currency": null,
      "unit": null
    },
    {
      "ticker": "GBPMAD=X",
      "name": "GBP / MAD",
      "price": 12.52,
      "trend": 3.35,
      "currency": null,
      "unit": null
    }
  ],
  "energy": [
    {
      "ticker": "BZ=F",
      "name": "Brent Crude",
      "price": 101.53,
      "trend": -3.61,
      "currency": "USD",
      "unit": "USD/bbl"
    },
    {
      "ticker": "CL=F",
      "name": "WTI Crude",
      "price": 95.98,
      "trend": 1.67,
      "currency": "USD",
      "unit": "USD/bbl"
    },
    {
      "ticker": "NG=F",
      "name": "Natural Gas",
      "price": 2.798,
      "trend": 10.9,
      "currency": "USD",
      "unit": "USD/MMBtu"
    },
    {
      "ticker": "HO=F",
      "name": "Heating Oil",
      "price": 3.9458,
      "trend": 1.5,
      "currency": "USD",
      "unit": "USD/gal"
    },
    {
      "ticker": "RB=F",
      "name": "Gasoline (RBOB)",
      "price": 3.3605,
      "trend": -2.95,
      "currency": "USD",
      "unit": "USD/gal"
    }
  ],
  "metals": [
    {
      "ticker": "GC=F",
      "name": "Gold",
      "price": 4705.6001,
      "trend": -0.35,
      "currency": "USD",
      "unit": "USD/oz"
    },
    {
      "ticker": "SI=F",
      "name": "Silver",
      "price": 75.285,
      "trend": -1.44,
      "currency": "USD",
      "unit": "USD/oz"
    },
    {
      "ticker": "HG=F",
      "name": "Copper",
      "price": 6.079,
      "trend": 0.92,
      "currency": "USD",
      "unit": "USD/lb"
    },
    {
      "ticker": "ALI=F",
      "name": "Aluminium",
      "price": 3522.25,
      "trend": -2.37,
      "currency": "USD",
      "unit": "USD/t"
    },
    {
      "ticker": "PL=F",
      "name": "Platinum",
      "price": 2007.9,
      "trend": -0.35,
      "currency": "USD",
      "unit": "USD/oz"
    },
    {
      "ticker": "PA=F",
      "name": "Palladium",
      "price": 1490.5,
      "trend": -0.73,
      "currency": "USD",
      "unit": "USD/oz"
    }
  ],
  "agriculture": [
    {
      "ticker": "SB=F",
      "name": "Sugar #11",
      "price": 14.11,
      "trend": 1.29,
      "currency": null,
      "unit": "¢/lb"
    },
    {
      "ticker": "KC=F",
      "name": "Coffee",
      "price": 290.9,
      "trend": -6.1,
      "currency": null,
      "unit": "¢/lb"
    },
    {
      "ticker": "CT=F",
      "name": "Cotton #2",
      "price": 80.3,
      "trend": 4.29,
      "currency": null,
      "unit": "¢/lb"
    },
    {
      "ticker": "ZW=F",
      "name": "Wheat",
      "price": 620.75,
      "trend": 2.06,
      "currency": null,
      "unit": "¢/bu"
    },
    {
      "ticker": "ZC=F",
      "name": "Corn",
      "price": 466.5,
      "trend": 2.53,
      "currency": null,
      "unit": "¢/bu"
    },
    {
      "ticker": "ZS=F",
      "name": "Soybeans",
      "price": 1184.25,
      "trend": 1.76,
      "currency": null,
      "unit": "¢/bu"
    }
  ],
  "rates": {
    "USD": 1.0,
    "EUR": 0.8515,
    "GBP": 0.7377,
    "JPY": 159.238,
    "CAD": 1.3599,
    "AUD": 1.3898,
    "CNY": 6.8223,
    "CHF": 0.784,
    "HKD": 7.837,
    "SGD": 1.2734,
    "SEK": 9.1978,
    "KRW": 1471.8101,
    "NOK": 9.2645,
    "NZD": 1.6894,
    "INR": 94.17,
    "MXN": 17.3649,
    "TWD": 31.411,
    "ZAR": 16.4993,
    "BRL": 4.9728,
    "DKK": 6.3644,
    "PLN": 3.6166,
    "THB": 32.31,
    "IDR": 17222.0,
    "HUF": 309.968,
    "CZK": 20.73,
    "ILS": 2.9801,
    "CLP": 892.87,
    "PHP": 60.72,
    "AED": 3.673,
    "COP": 3567.1001,
    "SAR": 3.7506,
    "MYR": 3.95,
    "RON": 4.3355,
    "MAD": 9.2435
  },
  "exchanger_audit": {
    "total_requested": 33,
    "fetched": 33,
    "validated": 33,
    "bounds_rejected": [],
    "fetch_failed": [],
    "cross_check_deviations": {},
    "cross_check_source": "ECB",
    "final_count": 34
  }
}