{
  "last_update": "2026-04-17T13:55:22.210568+00:00",
  "totalItems": 31,
  "indices": [
    {
      "ticker": "^GSPC",
      "name": "S&P 500",
      "price": 7100.2598,
      "trend": 0.84,
      "currency": null,
      "unit": "pts"
    },
    {
      "ticker": "^DJI",
      "name": "Dow Jones",
      "price": 49252.9219,
      "trend": 1.39,
      "currency": null,
      "unit": "pts"
    },
    {
      "ticker": "^IXIC",
      "name": "Nasdaq",
      "price": 24353.3047,
      "trend": 1.04,
      "currency": null,
      "unit": "pts"
    },
    {
      "ticker": "^STOXX50E",
      "name": "Euro Stoxx 50",
      "price": 6047.8999,
      "trend": 1.93,
      "currency": null,
      "unit": "pts"
    },
    {
      "ticker": "^FTSE",
      "name": "FTSE 100",
      "price": 10629.8301,
      "trend": 0.38,
      "currency": null,
      "unit": "pts"
    },
    {
      "ticker": "^N225",
      "name": "Nikkei 225",
      "price": 58475.8984,
      "trend": -1.75,
      "currency": null,
      "unit": "pts"
    }
  ],
  "currencies": [
    {
      "ticker": "EURUSD=X",
      "name": "EUR / USD",
      "price": 1.1837,
      "trend": 0.24,
      "currency": null,
      "unit": null
    },
    {
      "ticker": "USDJPY=X",
      "name": "USD / JPY",
      "price": 158.263,
      "trend": -0.34,
      "currency": null,
      "unit": null
    },
    {
      "ticker": "GBPUSD=X",
      "name": "GBP / USD",
      "price": 1.3575,
      "trend": 0.01,
      "currency": null,
      "unit": null
    },
    {
      "ticker": "USDCNY=X",
      "name": "USD / CNY",
      "price": 6.8173,
      "trend": -0.01,
      "currency": null,
      "unit": null
    },
    {
      "ticker": "DX-Y.NYB",
      "name": "US Dollar Index",
      "price": 97.749,
      "trend": -0.48,
      "currency": null,
      "unit": "pts"
    },
    {
      "ticker": "USDMAD=X",
      "name": "USD / MAD",
      "price": 9.2045,
      "trend": -0.28,
      "currency": null,
      "unit": null
    },
    {
      "ticker": "EURMAD=X",
      "name": "EUR / MAD",
      "price": 10.874,
      "trend": 3.05,
      "currency": null,
      "unit": null
    },
    {
      "ticker": "GBPMAD=X",
      "name": "GBP / MAD",
      "price": 12.476,
      "trend": 2.77,
      "currency": null,
      "unit": null
    }
  ],
  "energy": [
    {
      "ticker": "BZ=F",
      "name": "Brent Crude",
      "price": 88.89,
      "trend": -10.56,
      "currency": "USD",
      "unit": "USD/bbl"
    },
    {
      "ticker": "CL=F",
      "name": "WTI Crude",
      "price": 81.6,
      "trend": -13.82,
      "currency": "USD",
      "unit": "USD/bbl"
    },
    {
      "ticker": "NG=F",
      "name": "Natural Gas",
      "price": 2.652,
      "trend": 0.19,
      "currency": "USD",
      "unit": "USD/MMBtu"
    },
    {
      "ticker": "HO=F",
      "name": "Heating Oil",
      "price": 3.2467,
      "trend": -15.29,
      "currency": "USD",
      "unit": "USD/gal"
    },
    {
      "ticker": "RB=F",
      "name": "Gasoline (RBOB)",
      "price": 2.8673,
      "trend": -9.37,
      "currency": "USD",
      "unit": "USD/gal"
    }
  ],
  "metals": [
    {
      "ticker": "GC=F",
      "name": "Gold",
      "price": 4883.7998,
      "trend": 2.06,
      "currency": "USD",
      "unit": "USD/oz"
    },
    {
      "ticker": "SI=F",
      "name": "Silver",
      "price": 82.06,
      "trend": 4.39,
      "currency": "USD",
      "unit": "USD/oz"
    },
    {
      "ticker": "HG=F",
      "name": "Copper",
      "price": 6.0665,
      "trend": -0.09,
      "currency": "USD",
      "unit": "USD/lb"
    },
    {
      "ticker": "ALI=F",
      "name": "Aluminium",
      "price": 3485.0,
      "trend": -4.46,
      "currency": "USD",
      "unit": "USD/t"
    },
    {
      "ticker": "PL=F",
      "name": "Platinum",
      "price": 2134.0,
      "trend": 1.91,
      "currency": "USD",
      "unit": "USD/oz"
    },
    {
      "ticker": "PA=F",
      "name": "Palladium",
      "price": 1603.0,
      "trend": 2.07,
      "currency": "USD",
      "unit": "USD/oz"
    }
  ],
  "agriculture": [
    {
      "ticker": "SB=F",
      "name": "Sugar #11",
      "price": 13.54,
      "trend": -0.88,
      "currency": null,
      "unit": "¢/lb"
    },
    {
      "ticker": "KC=F",
      "name": "Coffee",
      "price": 284.5,
      "trend": -4.03,
      "currency": null,
      "unit": "¢/lb"
    },
    {
      "ticker": "CT=F",
      "name": "Cotton #2",
      "price": 79.06,
      "trend": 4.44,
      "currency": null,
      "unit": "¢/lb"
    },
    {
      "ticker": "ZW=F",
      "name": "Wheat",
      "price": 596.75,
      "trend": -0.29,
      "currency": null,
      "unit": "¢/bu"
    },
    {
      "ticker": "ZC=F",
      "name": "Corn",
      "price": 448.5,
      "trend": -0.61,
      "currency": null,
      "unit": "¢/bu"
    },
    {
      "ticker": "ZS=F",
      "name": "Soybeans",
      "price": 1153.0,
      "trend": -0.92,
      "currency": null,
      "unit": "¢/bu"
    }
  ],
  "rates": {
    "USD": 1.0,
    "EUR": 0.8448,
    "GBP": 0.7367,
    "JPY": 158.253,
    "CAD": 1.3672,
    "AUD": 1.386,
    "CNY": 6.8173,
    "CHF": 0.7793,
    "HKD": 7.8284,
    "SGD": 1.2682,
    "SEK": 9.1014,
    "KRW": 1463.36,
    "NOK": 9.3561,
    "NZD": 1.6891,
    "INR": 92.501,
    "MXN": 17.1774,
    "TWD": 31.441,
    "ZAR": 16.2078,
    "BRL": 4.9611,
    "DKK": 6.3149,
    "PLN": 3.5698,
    "THB": 31.79,
    "IDR": 17184.0,
    "HUF": 304.821,
    "CZK": 20.5143,
    "ILS": 2.9587,
    "CLP": 876.87,
    "PHP": 59.814,
    "AED": 3.6726,
    "COP": 3595.5,
    "SAR": 3.751,
    "MYR": 3.95,
    "RON": 4.3085,
    "MAD": 9.2047
  },
  "exchanger_audit": {
    "total_requested": 33,
    "fetched": 33,
    "validated": 33,
    "bounds_rejected": [],
    "fetch_failed": [],
    "cross_check_deviations": {},
    "cross_check_source": "ECB",
    "final_count": 34
  }
}